{
  "analyzedAt": "2017-08-21T06:19:51.127Z",
  "collected": {
    "metadata": {
      "name": "react",
      "scope": "unscoped",
      "version": "15.6.1",
      "description": "React is a JavaScript library for building user interfaces.",
      "keywords": ["react"],
      "date": "2017-06-15T00:05:12.756Z",
      "publisher": {
        "username": "gaearon",
        "email": "dan.abramov@gmail.com"
      },
      "maintainers": [{
        "username": "flarnie",
        "email": "flarnie.npm@gmail.com"
      }, {
        "username": "gaearon",
        "email": "dan.abramov@gmail.com"
      }, {
        "username": "trueadm",
        "email": "dg@domgan.com"
      }, {
        "username": "brianvaughn",
        "email": "briandavidvaughn@gmail.com"
      }, {
        "username": "fb",
        "email": "opensource+npm@fb.com"
      }, {
        "username": "spicyj",
        "email": "ben@benalpert.com"
      }],
      "repository": {
        "type": "git",
        "url": "git+https://github.com/facebook/react.git"
      },
      "links": {
        "npm": "https://www.npmjs.com/package/react",
        "homepage": "https://facebook.github.io/react/",
        "repository": "https://github.com/facebook/react",
        "bugs": "https://github.com/facebook/react/issues"
      },
      "license": "BSD-3-Clause",
      "dependencies": {
        "create-react-class": "^15.6.0",
        "fbjs": "^0.8.9",
        "loose-envify": "^1.1.0",
        "object-assign": "^4.1.0",
        "prop-types": "^15.5.10"
      },
      "releases": [{
        "from": "2017-07-22T00:00:00.000Z",
        "to": "2017-08-21T00:00:00.000Z",
        "count": 5
      }, {
        "from": "2017-05-23T00:00:00.000Z",
        "to": "2017-08-21T00:00:00.000Z",
        "count": 9
      }, {
        "from": "2017-02-22T00:00:00.000Z",
        "to": "2017-08-21T00:00:00.000Z",
        "count": 27
      }, {
        "from": "2016-08-21T00:00:00.000Z",
        "to": "2017-08-21T00:00:00.000Z",
        "count": 39
      }, {
        "from": "2015-08-22T00:00:00.000Z",
        "to": "2017-08-21T00:00:00.000Z",
        "count": 74
      }],
      "hasSelectiveFiles": true,
      "readme": "# react\n\nAn npm package to get you immediate access to [React](https://facebook.github.io/react/),\nwithout also requiring the JSX transformer. This is especially useful for cases where you\nwant to [`browserify`](https://github.com/substack/node-browserify) your module using\n`React`.\n\n**Note:** by default, React will be in development mode. The development version includes extra warnings about common mistakes, whereas the production version includes extra performance optimizations and strips all error messages.\n\nTo use React in production mode, set the environment variable `NODE_ENV` to `production`. A minifier that performs dead-code elimination such as [UglifyJS](https://github.com/mishoo/UglifyJS2) is recommended to completely remove the extra code present in development mode.\n\n## Example Usage\n\n```js\nvar React = require('react');\n```"
    },
    "npm": {
      "downloads": [{
        "from": "2017-08-20T00:00:00.000Z",
        "to": "2017-08-21T00:00:00.000Z",
        "count": 71458
      }, {
        "from": "2017-08-14T00:00:00.000Z",
        "to": "2017-08-21T00:00:00.000Z",
        "count": 1166204
      }, {
        "from": "2017-07-22T00:00:00.000Z",
        "to": "2017-08-21T00:00:00.000Z",
        "count": 4783899
      }, {
        "from": "2017-05-23T00:00:00.000Z",
        "to": "2017-08-21T00:00:00.000Z",
        "count": 14297165
      }, {
        "from": "2017-02-22T00:00:00.000Z",
        "to": "2017-08-21T00:00:00.000Z",
        "count": 25810230
      }, {
        "from": "2016-08-21T00:00:00.000Z",
        "to": "2017-08-21T00:00:00.000Z",
        "count": 41118429
      }],
      "dependentsCount": 11209,
      "starsCount": 563
    },
    "github": {
      "homepage": "https://facebook.github.io/react/",
      "starsCount": 73855,
      "forksCount": 13905,
      "subscribersCount": 4840,
      "issues": {
        "count": 10415,
        "openCount": 740,
        "distribution": {
          "3600": 1995,
          "10800": 924,
          "32400": 993,
          "97200": 1259,
          "291600": 979,
          "874800": 939,
          "2624400": 844,
          "7873200": 730,
          "23619600": 870,
          "70858800": 713,
          "212576400": 169
        },
        "isDisabled": false
      },
      "contributors": [{
        "username": "zpao",
        "commitsCount": 820
      }, {
        "username": "spicyj",
        "commitsCount": 816
      }, {
        "username": "sebmarkbage",
        "commitsCount": 465
      }, {
        "username": "gaearon",
        "commitsCount": 441
      }, {
        "username": "acdlite",
        "commitsCount": 275
      }, {
        "username": "petehunt",
        "commitsCount": 205
      }, {
        "username": "chenglou",
        "commitsCount": 152
      }, {
        "username": "vjeux",
        "commitsCount": 140
      }, {
        "username": "jimfb",
        "commitsCount": 116
      }, {
        "username": "jeffmo",
        "commitsCount": 111
      }, {
        "username": "subtleGradient",
        "commitsCount": 110
      }, {
        "username": "bvaughn",
        "commitsCount": 106
      }, {
        "username": "benjamn",
        "commitsCount": 89
      }, {
        "username": "yungsters",
        "commitsCount": 74
      }, {
        "username": "syranide",
        "commitsCount": 69
      }, {
        "username": "nhunzaker",
        "commitsCount": 62
      }, {
        "username": "cpojer",
        "commitsCount": 51
      }, {
        "username": "trueadm",
        "commitsCount": 48
      }, {
        "username": "marocchino",
        "commitsCount": 45
      }, {
        "username": "koba04",
        "commitsCount": 45
      }, {
        "username": "aweary",
        "commitsCount": 45
      }, {
        "username": "kohei-takata",
        "commitsCount": 39
      }, {
        "username": "flarnie",
        "commitsCount": 33
      }, {
        "username": "keyanzhang",
        "commitsCount": 30
      }, {
        "username": "chicoxyzzy",
        "commitsCount": 29
      }, {
        "username": "mcsheffrey",
        "commitsCount": 21
      }, {
        "username": "joshduck",
        "commitsCount": 21
      }, {
        "username": "aickin",
        "commitsCount": 18
      }, {
        "username": "hellendag",
        "commitsCount": 17
      }, {
        "username": "Daniel15",
        "commitsCount": 16
      }, {
        "username": "fabiomcosta",
        "commitsCount": 15
      }, {
        "username": "bgw",
        "commitsCount": 14
      }, {
        "username": "crm416",
        "commitsCount": 14
      }, {
        "username": "arkist",
        "commitsCount": 14
      }, {
        "username": "cody",
        "commitsCount": 14
      }, {
        "username": "iamchenxin",
        "commitsCount": 13
      }, {
        "username": "tomocchino",
        "commitsCount": 13
      }, {
        "username": "mroch",
        "commitsCount": 12
      }, {
        "username": "Simek",
        "commitsCount": 12
      }, {
        "username": "ivanzotov",
        "commitsCount": 11
      }, {
        "username": "edvinerikson",
        "commitsCount": 11
      }, {
        "username": "kmeht",
        "commitsCount": 10
      }, {
        "username": "fisherwebdev",
        "commitsCount": 10
      }, {
        "username": "DarkScorpion",
        "commitsCount": 10
      }, {
        "username": "iamdustan",
        "commitsCount": 10
      }, {
        "username": "jquense",
        "commitsCount": 10
      }, {
        "username": "rayqian",
        "commitsCount": 9
      }, {
        "username": "RReverser",
        "commitsCount": 9
      }, {
        "username": "jaredly",
        "commitsCount": 9
      }, {
        "username": "AnSavvides",
        "commitsCount": 9
      }, {
        "username": "andreypopp",
        "commitsCount": 9
      }, {
        "username": "yiminghe",
        "commitsCount": 9
      }, {
        "username": "rickbeerendonk",
        "commitsCount": 9
      }, {
        "username": "SanderSpies",
        "commitsCount": 8
      }, {
        "username": "jgebhardt",
        "commitsCount": 8
      }, {
        "username": "kassens",
        "commitsCount": 8
      }, {
        "username": "camsong",
        "commitsCount": 8
      }, {
        "username": "bhamodi",
        "commitsCount": 8
      }, {
        "username": "hzoo",
        "commitsCount": 8
      }, {
        "username": "graue",
        "commitsCount": 8
      }, {
        "username": "dotu",
        "commitsCount": 8
      }, {
        "username": "zertosh",
        "commitsCount": 8
      }, {
        "username": "dittos",
        "commitsCount": 8
      }, {
        "username": "wincent",
        "commitsCount": 8
      }, {
        "username": "andrewdavey",
        "commitsCount": 7
      }, {
        "username": "yangshun",
        "commitsCount": 7
      }, {
        "username": "RaitoBezarius",
        "commitsCount": 7
      }, {
        "username": "bripkens",
        "commitsCount": 6
      }, {
        "username": "lrowe",
        "commitsCount": 6
      }, {
        "username": "matthewwithanm",
        "commitsCount": 6
      }, {
        "username": "piranha",
        "commitsCount": 6
      }, {
        "username": "mzabriskie",
        "commitsCount": 6
      }, {
        "username": "awwright",
        "commitsCount": 6
      }, {
        "username": "Pouja",
        "commitsCount": 6
      }, {
        "username": "makky3939",
        "commitsCount": 6
      }, {
        "username": "lyip1992",
        "commitsCount": 6
      }, {
        "username": "steveluscher",
        "commitsCount": 6
      }, {
        "username": "bspaulding",
        "commitsCount": 6
      }, {
        "username": "ianobermiller",
        "commitsCount": 6
      }, {
        "username": "mxstbr",
        "commitsCount": 6
      }, {
        "username": "jontewks",
        "commitsCount": 6
      }, {
        "username": "aaronabramov",
        "commitsCount": 6
      }, {
        "username": "brigand",
        "commitsCount": 6
      }, {
        "username": "clayallsopp",
        "commitsCount": 5
      }, {
        "username": "keito",
        "commitsCount": 5
      }, {
        "username": "jbaiter",
        "commitsCount": 5
      }, {
        "username": "jordwalke",
        "commitsCount": 5
      }, {
        "username": "joshma",
        "commitsCount": 5
      }, {
        "username": "pedronauck",
        "commitsCount": 5
      }, {
        "username": "ClimbsRocks",
        "commitsCount": 5
      }, {
        "username": "jeyraof",
        "commitsCount": 5
      }, {
        "username": "dalinaum",
        "commitsCount": 5
      }, {
        "username": "julen",
        "commitsCount": 5
      }, {
        "username": "drd",
        "commitsCount": 5
      }, {
        "username": "jbonta",
        "commitsCount": 5
      }, {
        "username": "matthewjohnston4",
        "commitsCount": 5
      }, {
        "username": "hejld",
        "commitsCount": 5
      }, {
        "username": "sairion",
        "commitsCount": 5
      }, {
        "username": "puradox",
        "commitsCount": 5
      }, {
        "username": "elas7",
        "commitsCount": 5
      }],
      "commits": [{
        "from": "2017-08-14T00:00:00.000Z",
        "to": "2017-08-21T00:00:00.000Z",
        "count": 0
      }, {
        "from": "2017-07-22T00:00:00.000Z",
        "to": "2017-08-21T00:00:00.000Z",
        "count": 111
      }, {
        "from": "2017-05-23T00:00:00.000Z",
        "to": "2017-08-21T00:00:00.000Z",
        "count": 280
      }, {
        "from": "2017-02-22T00:00:00.000Z",
        "to": "2017-08-21T00:00:00.000Z",
        "count": 654
      }, {
        "from": "2016-08-21T00:00:00.000Z",
        "to": "2017-08-21T00:00:00.000Z",
        "count": 1663
      }],
      "statuses": [{
        "context": "ci/circleci",
        "state": "success"
      }, {
        "context": "coverage/coveralls",
        "state": "success"
      }]
    },
    "source": {
      "files": {
        "readmeSize": 849,
        "testsSize": 1548322,
        "hasChangelog": true
      },
      "badges": [{
        "urls": {
          "original": "https://img.shields.io/coveralls/facebook/react/master.svg?style=flat",
          "service": "https://coveralls.io/repos/facebook/react/badge.svg?branch=master",
          "shields": "https://img.shields.io/coveralls/facebook/react/master.svg",
          "content": "https://img.shields.io/coveralls/facebook/react/master.json"
        },
        "info": {
          "service": "coveralls",
          "type": "coverage",
          "modifiers": {
            "branch": "master"
          }
        }
      }, {
        "urls": {
          "original": "https://img.shields.io/npm/v/react.svg?style=flat",
          "shields": "https://img.shields.io/npm/v/react.svg",
          "content": "https://img.shields.io/npm/v/react.json"
        },
        "info": {
          "service": "npm",
          "type": "version",
          "modifiers": {
            "type": "v"
          }
        }
      }],
      "linters": {
        "general": ["editorconfig"],
        "js": ["eslint"]
      },
      "coverage": 0.9,
      "outdatedDependencies": {
        "fbjs": {
          "required": "^0.8.9",
          "stable": "0.8.14",
          "latest": "0.9.0-alpha.2"
        }
      }
    }
  },
  "evaluation": {
    "quality": {
      "carefulness": 0.9999999999999999,
      "tests": 0.685,
      "health": 0.75,
      "branding": 0.7
    },
    "popularity": {
      "communityInterest": 93263,
      "downloadsCount": 4765721.666666667,
      "downloadsAcceleration": 19386.751598173512,
      "dependentsCount": 11209
    },
    "maintenance": {
      "releasesFrequency": 1,
      "commitsFrequency": 1,
      "openIssues": 1,
      "issuesDistribution": 0.42988473557284307
    }
  },
  "score": {
    "final": 0.9362727213231605,
    "detail": {
      "quality": 0.9450633140685243,
      "popularity": 0.9153093735615945,
      "maintenance": 0.9497012753029865
    }
  }
}